{
    "annotations": {
      "list": [
        {
          "builtIn": 1,
          "datasource": {
            "type": "grafana",
            "uid": "-- Grafana --"
          },
          "enable": true,
          "hide": true,
          "iconColor": "rgba(0, 211, 255, 1)",
          "name": "Annotations & Alerts",
          "type": "dashboard"
        }
      ]
    },
    "editable": true,
    "fiscalYearStartMonth": 0,
    "graphTooltip": 0,
    "id": 8,
    "links": [],
    "panels": [
      {
        "datasource": {
          "type": "loki",
          "uid": "P8E80F9AEF21F6940"
        },
        "fieldConfig": {
          "defaults": {},
          "overrides": []
        },
        "gridPos": {
          "h": 8,
          "w": 12,
          "x": 0,
          "y": 0
        },
        "id": 2,
        "options": {
          "dedupStrategy": "none",
          "enableLogDetails": true,
          "prettifyLogMessage": false,
          "showCommonLabels": false,
          "showLabels": false,
          "showTime": true,
          "sortOrder": "Descending",
          "wrapLogMessage": false
        },
        "pluginVersion": "11.3.1",
        "targets": [
          {
            "datasource": {
              "type": "loki",
              "uid": "P8E80F9AEF21F6940"
            },
            "editorMode": "builder",
            "expr": "{service_name=\"app-backend-1\"} |= ``",
            "queryType": "range",
            "refId": "A"
          }
        ],
        "title": "backend",
        "type": "logs"
      },
      {
        "datasource": {
          "type": "loki",
          "uid": "P8E80F9AEF21F6940"
        },
        "fieldConfig": {
          "defaults": {},
          "overrides": []
        },
        "gridPos": {
          "h": 8,
          "w": 12,
          "x": 12,
          "y": 0
        },
        "id": 3,
        "options": {
          "dedupStrategy": "none",
          "enableLogDetails": true,
          "prettifyLogMessage": false,
          "showCommonLabels": false,
          "showLabels": false,
          "showTime": true,
          "sortOrder": "Descending",
          "wrapLogMessage": false
        },
        "pluginVersion": "11.3.1",
        "targets": [
          {
            "datasource": {
              "type": "loki",
              "uid": "P8E80F9AEF21F6940"
            },
            "editorMode": "builder",
            "expr": "{service_name=\"app-frontend-1\"} |= ``",
            "queryType": "range",
            "refId": "A"
          }
        ],
        "title": "Frontend",
        "type": "logs"
      },
      {
        "datasource": {
          "type": "loki",
          "uid": "P8E80F9AEF21F6940"
        },
        "fieldConfig": {
          "defaults": {},
          "overrides": []
        },
        "gridPos": {
          "h": 6,
          "w": 24,
          "x": 0,
          "y": 8
        },
        "id": 4,
        "options": {
          "dedupStrategy": "none",
          "enableLogDetails": true,
          "prettifyLogMessage": false,
          "showCommonLabels": false,
          "showLabels": false,
          "showTime": true,
          "sortOrder": "Descending",
          "wrapLogMessage": false
        },
        "pluginVersion": "11.3.1",
        "targets": [
          {
            "datasource": {
              "type": "loki",
              "uid": "P8E80F9AEF21F6940"
            },
            "editorMode": "builder",
            "expr": "{service_name=\"app-database-1\"} |= ``",
            "queryType": "range",
            "refId": "A"
          }
        ],
        "title": "Database",
        "type": "logs"
      },
      {
        "datasource": {
          "type": "loki",
          "uid": "P8E80F9AEF21F6940"
        },
        "fieldConfig": {
          "defaults": {},
          "overrides": []
        },
        "gridPos": {
          "h": 7,
          "w": 24,
          "x": 0,
          "y": 14
        },
        "id": 1,
        "options": {
          "dedupStrategy": "none",
          "enableLogDetails": true,
          "prettifyLogMessage": false,
          "showCommonLabels": false,
          "showLabels": false,
          "showTime": true,
          "sortOrder": "Descending",
          "wrapLogMessage": false
        },
        "pluginVersion": "11.3.1",
        "targets": [
          {
            "datasource": {
              "type": "loki",
              "uid": "P8E80F9AEF21F6940"
            },
            "editorMode": "builder",
            "expr": "{service_name=\"varlogs\"} |= ``",
            "queryType": "range",
            "refId": "A"
          }
        ],
        "title": "Var Logs",
        "type": "logs"
      }
    ],
    "preload": false,
    "schemaVersion": 40,
    "tags": [],
    "templating": {
      "list": []
    },
    "time": {
      "from": "now-3h",
      "to": "now"
    },
    "timepicker": {},
    "timezone": "browser",
    "title": "Logs",
    "uid": "ae5vtue1kvncwb",
    "version": 6,
    "weekStart": ""
  }